affinder/__init__.py
affinder/_test_data.py
affinder/_version.py
affinder/affinder.py
affinder/apply_tf.py
affinder/copy_tf.py
affinder/load_tf.py
affinder/main.py
affinder/napari.yaml
affinder/_tests/__init__.py
affinder/_tests/test_affinder.py
affinder-0.4.0.dist-info/LICENSE
affinder-0.4.0.dist-info/METADATA
affinder-0.4.0.dist-info/WHEEL
affinder-0.4.0.dist-info/entry_points.txt
affinder-0.4.0.dist-info/top_level.txt
affinder-0.4.0.dist-info/RECORD
