Metadata-Version: 2.1
Name: affinder
Version: 0.4.0
Summary: Quickly find the affine matrix mapping one image to another using manual correspondence points annotation
Home-page: https://github.com/jni/affinder
Author: Juan Nunez-Iglesias
Author-email: juan.nunez-iglesias@monash.edu
License: BSD-3
Classifier: Development Status :: 3 - Alpha
Classifier: Intended Audience :: Developers
Classifier: Framework :: napari
Classifier: Topic :: Software Development :: Testing
Classifier: Programming Language :: Python
Classifier: Programming Language :: Python :: 3
Classifier: Programming Language :: Python :: 3.9
Classifier: Programming Language :: Python :: 3.10
Classifier: Programming Language :: Python :: 3.11
Classifier: Operating System :: OS Independent
Classifier: License :: OSI Approved :: BSD License
Requires-Python: >=3.9
License-File: LICENSE
Requires-Dist: napari >=0.4.17
Requires-Dist: npe2 >=0.1.2
Requires-Dist: numpy
Requires-Dist: scikit-image >=0.19.2
Requires-Dist: magicgui >=0.3.7
Requires-Dist: toolz
Provides-Extra: docs
Requires-Dist: furo ; extra == 'docs'
Requires-Dist: myst-parser ; extra == 'docs'
Provides-Extra: testing
Requires-Dist: coverage ; extra == 'testing'
Requires-Dist: pydantic <2 ; extra == 'testing'
Requires-Dist: pytest ; extra == 'testing'
Requires-Dist: pytest-cov ; extra == 'testing'
Requires-Dist: pytest-qt ; extra == 'testing'
Requires-Dist: scikit-image[data] ; extra == 'testing'
Requires-Dist: napari[pyqt5] !=0.4.18 ; extra == 'testing'
Requires-Dist: pygments !=2.16 ; extra == 'testing'
Requires-Dist: zarr ; extra == 'testing'
